MANIFEST.in
README
setup.py
django_mongodb_cache.egg-info/PKG-INFO
django_mongodb_cache.egg-info/SOURCES.txt
django_mongodb_cache.egg-info/dependency_links.txt
django_mongodb_cache.egg-info/top_level.txt
mongodb_cache/__init__.py