Metadata-Version: 1.0
Name: django-mongodb-cache
Version: 0.1.0
Summary: Mongodb cache backend for Django framework
Home-page: http://bitbucket.org/lorien/django-mongodb-cache/
Author: Grigoriy Petukhov
Author-email: lorien@lorien.name
License: BSD
Keywords: django cache mongodb
Platform: UNKNOWN
Classifier: Development Status :: 4 - Beta
Classifier: Environment :: Web Environment
Classifier: Framework :: Django
Classifier: Intended Audience :: Developers
Classifier: License :: OSI Approved :: BSD License
Classifier: Operating System :: OS Independent
Classifier: Programming Language :: Python
Classifier: Topic :: Software Development :: Libraries :: Python Modules
